setup.cfg
setup.py
stockfighter/__init__.py
stockfighter/exchange.py
stockfighter/utils.py
stockfighter/api/__init__.py
stockfighter/api/exchange.py
stockfighter/api/game.py
stockfighter/api/utils.py
stockfighter/api/websocket.py
stockfighter_io.egg-info/PKG-INFO
stockfighter_io.egg-info/SOURCES.txt
stockfighter_io.egg-info/dependency_links.txt
stockfighter_io.egg-info/requires.txt
stockfighter_io.egg-info/top_level.txt