Metadata-Version: 1.1
Name: stockfighter-io
Version: 0.1.10
Summary: An API wrapper for Stockfighter.io
Home-page: https://github.com/karma0/stockfighter
Author: Bobby Larson
Author-email: karma0@gmail.com
License: UNKNOWN
Download-URL: https://github.com/karma0/stockfighter/tarball/0.1
Keywords: stockfighter,exchange,trades
Platform: UNKNOWN
